{"__symbolic":"module","version":4,"metadata":{"AuthService":{"__symbolic":"class","decorators":[{"__symbolic":"call","expression":{"__symbolic":"reference","module":"@angular/core","name":"Injectable","line":16,"character":1},"arguments":[{"providedIn":"root"}]}],"members":{"__ctor__":[{"__symbolic":"constructor","parameterDecorators":[[{"__symbolic":"call","expression":{"__symbolic":"reference","module":"@angular/core","name":"Inject","line":25,"character":3},"arguments":[{"__symbolic":"reference","module":"@angular/core","name":"PLATFORM_ID","line":25,"character":10}]}],null,null],"parameters":[{"__symbolic":"reference","name":"string"},{"__symbolic":"reference","module":"@angular/core","name":"Injector","line":26,"character":20},{"__symbolic":"reference","name":"LocalStorageService"}]}],"setToken":[{"__symbolic":"method"}],"getToken":[{"__symbolic":"method"}],"getFakeToken":[{"__symbolic":"method"}],"isValid":[{"__symbolic":"method"}],"isAuthenticated":[{"__symbolic":"method"}],"collectFailedRequest":[{"__symbolic":"method"}],"retryFailedRequests":[{"__symbolic":"method"}]},"statics":{"ngInjectableDef":{}}},"AuthStrategy":{"Bearer":0,"Cookie":1},"CoreConfig":{"__symbolic":"class","members":{"__ctor__":[{"__symbolic":"constructor","parameters":[{"__symbolic":"reference","name":"CoreConfig"}]}]}},"CORE_CONFIG":{"__symbolic":"new","expression":{"__symbolic":"reference","module":"@angular/core","name":"InjectionToken","line":60,"character":31},"arguments":["core.config"]},"CoreService":{"__symbolic":"class","decorators":[{"__symbolic":"call","expression":{"__symbolic":"reference","module":"@angular/core","name":"Injectable","line":4,"character":1},"arguments":[{"providedIn":"root"}]}],"members":{"__ctor__":[{"__symbolic":"constructor","parameterDecorators":[[{"__symbolic":"call","expression":{"__symbolic":"reference","module":"@angular/core","name":"Inject","line":12,"character":3},"arguments":[{"__symbolic":"reference","name":"CORE_CONFIG"}]}]],"parameters":[{"__symbolic":"reference","name":"CoreConfig"}]}]},"statics":{"ngInjectableDef":{}}},"DefaultContentDirective":{"__symbolic":"class","decorators":[{"__symbolic":"call","expression":{"__symbolic":"reference","module":"@angular/core","name":"Directive","line":2,"character":1},"arguments":[{"selector":"[default]"}]}],"members":{"default":[{"__symbolic":"property","decorators":[{"__symbolic":"call","expression":{"__symbolic":"reference","module":"@angular/core","name":"Input","line":7,"character":2}}]}],"__ctor__":[{"__symbolic":"constructor","parameters":[{"__symbolic":"reference","module":"@angular/core","name":"ElementRef","line":12,"character":11},{"__symbolic":"reference","module":"@angular/core","name":"ViewContainerRef","line":13,"character":21},{"__symbolic":"reference","module":"@angular/core","name":"Renderer2","line":14,"character":20}]}],"ngAfterContentChecked":[{"__symbolic":"method"}]}},"CoreModuleComponent":{"__symbolic":"class","decorators":[{"__symbolic":"call","expression":{"__symbolic":"reference","module":"@angular/core","name":"Component","line":2,"character":1},"arguments":[{"selector":"core-module","template":"<span class=\"core-module\">core {{version}}</span>","styles":[]}]}],"members":{"__ctor__":[{"__symbolic":"constructor"}],"ngOnInit":[{"__symbolic":"method"}]}},"CoreModule":{"__symbolic":"class","decorators":[{"__symbolic":"call","expression":{"__symbolic":"reference","module":"@angular/core","name":"NgModule","line":102,"character":1},"arguments":[{"imports":[{"__symbolic":"reference","module":"@angular/common","name":"CommonModule","line":104,"character":2},{"__symbolic":"reference","module":"@angular/common/http","name":"HttpClientModule","line":105,"character":2},{"__symbolic":"reference","module":"@angular/forms","name":"FormsModule","line":106,"character":2},{"__symbolic":"reference","module":"@angular/forms","name":"ReactiveFormsModule","line":107,"character":2}],"providers":[{"provide":{"__symbolic":"reference","module":"@angular/common/http","name":"HTTP_INTERCEPTORS","line":110,"character":13},"useClass":{"__symbolic":"reference","name":"HttpResponseInterceptor"},"multi":true},{"__symbolic":"reference","name":"AuthService"},{"__symbolic":"reference","name":"CoreService"},{"__symbolic":"reference","name":"ControlService"},{"__symbolic":"reference","name":"CookieStorageService"},{"__symbolic":"reference","name":"EventDispatcherService"},{"__symbolic":"reference","name":"FormService"},{"__symbolic":"reference","name":"HttpStatusCodeService"},{"__symbolic":"reference","name":"LabelService"},{"__symbolic":"reference","name":"LocalStorageService"},{"__symbolic":"reference","name":"Logger"},{"__symbolic":"reference","name":"MenuService"},{"__symbolic":"reference","name":"OnceService"},{"__symbolic":"reference","name":"SessionStorageService"},{"__symbolic":"reference","name":"StorageService"},{"__symbolic":"reference","name":"AssetPipe"},{"__symbolic":"reference","name":"CustomAsyncPipe"},{"__symbolic":"reference","name":"HighlightPipe"},{"__symbolic":"reference","name":"ImagePipe"},{"__symbolic":"reference","name":"ImageUrlPipe"},{"__symbolic":"reference","name":"LabelAsyncPipe"},{"__symbolic":"reference","name":"LabelPipe"},{"__symbolic":"reference","name":"PublicPipe"},{"__symbolic":"reference","name":"RoutePipe"},{"__symbolic":"reference","name":"SafeStylePipe"},{"__symbolic":"reference","name":"SafeUrlPipe"},{"__symbolic":"reference","name":"SegmentPipe"},{"__symbolic":"reference","name":"SlugAsyncPipe"},{"__symbolic":"reference","name":"SlugPipe"},{"__symbolic":"reference","name":"TranslatePipe"},{"__symbolic":"reference","name":"TrustPipe"},{"__symbolic":"reference","name":"ExistsValidator"},{"__symbolic":"reference","name":"MatchValidator"}],"declarations":[{"__symbolic":"reference","name":"ControlComponent"},{"__symbolic":"reference","name":"CoreModuleComponent"},{"__symbolic":"reference","name":"DisposableComponent"},{"__symbolic":"reference","name":"JsonFormatterComponent"},{"__symbolic":"reference","name":"LoggerComponent"},{"__symbolic":"reference","name":"DefaultContentDirective"},{"__symbolic":"reference","name":"LabelDirective"},{"__symbolic":"reference","name":"UppercaseDirective"},{"__symbolic":"reference","name":"AssetPipe"},{"__symbolic":"reference","name":"CustomAsyncPipe"},{"__symbolic":"reference","name":"HighlightPipe"},{"__symbolic":"reference","name":"ImagePipe"},{"__symbolic":"reference","name":"ImageUrlPipe"},{"__symbolic":"reference","name":"LabelAsyncPipe"},{"__symbolic":"reference","name":"LabelPipe"},{"__symbolic":"reference","name":"PublicPipe"},{"__symbolic":"reference","name":"RoutePipe"},{"__symbolic":"reference","name":"SafeStylePipe"},{"__symbolic":"reference","name":"SafeUrlPipe"},{"__symbolic":"reference","name":"SegmentPipe"},{"__symbolic":"reference","name":"SlugAsyncPipe"},{"__symbolic":"reference","name":"SlugPipe"},{"__symbolic":"reference","name":"TranslatePipe"},{"__symbolic":"reference","name":"TrustPipe"},{"__symbolic":"reference","name":"ExistsValidator"},{"__symbolic":"reference","name":"MatchValidator"}],"exports":[{"__symbolic":"reference","name":"ControlComponent"},{"__symbolic":"reference","name":"CoreModuleComponent"},{"__symbolic":"reference","name":"DisposableComponent"},{"__symbolic":"reference","name":"JsonFormatterComponent"},{"__symbolic":"reference","name":"LoggerComponent"},{"__symbolic":"reference","name":"DefaultContentDirective"},{"__symbolic":"reference","name":"LabelDirective"},{"__symbolic":"reference","name":"UppercaseDirective"},{"__symbolic":"reference","name":"AssetPipe"},{"__symbolic":"reference","name":"CustomAsyncPipe"},{"__symbolic":"reference","name":"HighlightPipe"},{"__symbolic":"reference","name":"ImagePipe"},{"__symbolic":"reference","name":"ImageUrlPipe"},{"__symbolic":"reference","name":"LabelAsyncPipe"},{"__symbolic":"reference","name":"LabelPipe"},{"__symbolic":"reference","name":"PublicPipe"},{"__symbolic":"reference","name":"RoutePipe"},{"__symbolic":"reference","name":"SafeStylePipe"},{"__symbolic":"reference","name":"SafeUrlPipe"},{"__symbolic":"reference","name":"SegmentPipe"},{"__symbolic":"reference","name":"SlugAsyncPipe"},{"__symbolic":"reference","name":"SlugPipe"},{"__symbolic":"reference","name":"TranslatePipe"},{"__symbolic":"reference","name":"TrustPipe"},{"__symbolic":"reference","name":"ExistsValidator"},{"__symbolic":"reference","name":"MatchValidator"}]}]}],"members":{"__ctor__":[{"__symbolic":"constructor","parameterDecorators":[[{"__symbolic":"call","expression":{"__symbolic":"reference","module":"@angular/core","name":"Optional","line":132,"character":3}},{"__symbolic":"call","expression":{"__symbolic":"reference","module":"@angular/core","name":"SkipSelf","line":132,"character":15}}]],"parameters":[{"__symbolic":"reference","name":"CoreModule"}]}]},"statics":{"forRoot":{"__symbolic":"function","parameters":["config"],"value":{"ngModule":{"__symbolic":"reference","name":"CoreModule"},"providers":[{"provide":{"__symbolic":"reference","name":"CORE_CONFIG"},"useValue":{"__symbolic":"reference","name":"config"}}]}}}},"DisposableComponent":{"__symbolic":"class","decorators":[{"__symbolic":"call","expression":{"__symbolic":"reference","module":"@angular/core","name":"Component","line":4,"character":1},"arguments":[{"template":""}]}],"members":{"ngOnDestroy":[{"__symbolic":"method"}]}},"ControlBase":{"__symbolic":"class","arity":1,"members":{"__ctor__":[{"__symbolic":"constructor","parameters":[{"__symbolic":"reference","name":"ControlBaseOptions"}]}]},"statics":{"uid":0}},"ControlBaseOptions":{"__symbolic":"class","arity":1,"members":{}},"ControlComponent":{"__symbolic":"class","decorators":[{"__symbolic":"call","expression":{"__symbolic":"reference","module":"@angular/core","name":"Component","line":4,"character":1},"arguments":[{"selector":"core-control","providers":[{"provide":{"__symbolic":"reference","module":"@angular/forms","name":"NG_VALUE_ACCESSOR","line":8,"character":11},"useExisting":{"__symbolic":"reference","name":"ControlComponent"},"multi":true}],"template":"<ng-container [ngSwitch]=\"control.schema\">\r\n\t<ng-container *ngSwitchCase=\"'checkbox'\">\r\n\t\t<b>Checkbox</b><br>\r\n\t</ng-container>\r\n\t<ng-container *ngSwitchCase=\"'email'\">\r\n\t\t<b>Email</b><br>\r\n\t</ng-container>\r\n\t<ng-container *ngSwitchCase=\"'number'\">\r\n\t\t<b>Number</b><br>\r\n\t</ng-container>\r\n\t<ng-container *ngSwitchCase=\"'password'\">\r\n\t\t<b>Password</b><br>\r\n\t</ng-container>\r\n</ng-container>\r\n<div class=\"form-group\" [formGroup]=\"form\">\r\n\t<div [ngSwitch]=\"control.schema\">\r\n\t\t<div *ngSwitchCase=\"'checkbox'\" class=\"form-group\">\r\n\t\t\t<!-- CHECKBOX -->\r\n\t\t\t<div class=\"checkbox\">\r\n\t\t\t\t<label>\r\n\t\t\t\t\t<input type=\"checkbox\" class=\"form-check-input\" [id]=\"control.key\" [formControlName]=\"control.key\">\r\n\t\t\t\t\t<span>{{ control.label | translate }}</span>\r\n\t\t\t\t</label>\r\n\t\t\t</div>\r\n\t\t</div>\r\n\t\t<div *ngSwitchCase=\"'email'\">\r\n\t\t\t<!-- EMAIL -->\r\n\t\t\t<label [attr.for]=\"control.key\">{{ control.label | translate }}</label>\r\n\t\t\t<input placeholder=\"{{ control.placeholder | translate }}\" class=\"form-control\" [id]=\"control.key\" [formControlName]=\"control.key\" [type]=\"control.type\">\r\n\t\t</div>\r\n\t\t<div *ngSwitchCase=\"'number'\">\r\n\t\t\t<!-- NUMBER -->\r\n\t\t\t<label [attr.for]=\"control.key\">{{ control.label | translate }}</label>\r\n\t\t\t<input placeholder=\"{{ control.placeholder | translate }}\" class=\"form-control\" [id]=\"control.key\" [type]=\"control.type\" [attr.step]=\"control.step\" (input)=\"onInput($event)\" (focus)=\"onFocus($event)\" (blur)=\"onBlur($event)\" [value]=\"getFormattedValue()\">\r\n\t\t</div>\r\n\t\t<div *ngSwitchCase=\"'password'\">\r\n\t\t\t<!-- PASSWORD -->\r\n\t\t\t<label [attr.for]=\"control.key\">{{ control.label | translate }}</label>\r\n\t\t\t<div class=\"input-group\">\r\n\t\t\t\t<input placeholder=\"{{ control.placeholder | translate }}\" class=\"form-control\" [id]=\"control.key\" [formControlName]=\"control.key\" [type]=\"control.type\" #password>\r\n\t\t\t\t<div class=\"input-group-append\" *ngIf=\"control.type === 'password'\">\r\n\t\t\t\t\t<div class=\"input-group-text\">\r\n\t\t\t\t\t\t<input type=\"checkbox\" [attr.aria-label]=\"control.label | translate\" (input)=\"password.type = reveal.checked ? 'text' : control.type\" #password>\r\n\t\t\t\t\t</div>\r\n\t\t\t\t</div>\r\n\t\t\t</div>\r\n\t\t</div>\r\n\t\t<div *ngSwitchCase=\"'radio'\" class=\"form-group\">\r\n\t\t\t<!-- RADIO -->\r\n\t\t\t<div class=\"radio\">\r\n\t\t\t\t<label>\r\n\t\t\t\t\t<input type=\"radio\" class=\"form-radio-input\" [id]=\"control.key\" [formControlName]=\"control.key\">\r\n\t\t\t\t\t<span>{{ control.label | translate }}</span>\r\n\t\t\t\t</label>\r\n\t\t\t</div>\r\n\t\t</div>\r\n\t\t<div *ngSwitchCase=\"'select'\">\r\n\t\t\t<!-- SELECT -->\r\n\t\t\t<label [attr.for]=\"control.key\">{{ control.label | translate }}</label>\r\n\t\t\t<select class=\"form-control\" [id]=\"control.key\" [formControlName]=\"control.key\">\r\n\t\t\t\t<option *ngFor=\"let opt of control.options\" [value]=\"opt.key\">{{opt.value}}</option>\r\n\t\t\t</select>\r\n\t\t</div>\r\n\t\t<div *ngSwitchCase=\"'markdown'\">\r\n\t\t\t<!-- MARKDOWN -->\r\n\t\t\t<label [attr.for]=\"control.key\">{{ control.label | translate }}</label>\r\n\t\t\t<textarea placeholder=\"{{ control.placeholder | translate }}\" class=\"form-control\" [id]=\"control.key\" [formControlName]=\"control.key\" rows=\"4\"></textarea>\r\n\t\t</div>\r\n\t\t<div *ngSwitchCase=\"'text'\">\r\n\t\t\t<!-- TEXT -->\r\n\t\t\t<label [attr.for]=\"control.key\">{{ control.label | translate }}</label>\r\n\t\t\t<input placeholder=\"{{ control.placeholder | translate }}\" class=\"form-control\" [id]=\"control.key\" [formControlName]=\"control.key\" [type]=\"control.type\">\r\n\t\t</div>\r\n\t</div>\r\n\t<div *ngIf=\"controlRef.invalid && (controlRef.dirty || controlRef.touched)\" class=\"alert alert-danger\">\r\n\t\t<div *ngIf=\"controlRef.errors.required\">{{ 'errors.required' | translate }}</div>\r\n\t\t<div *ngIf=\"controlRef.errors.requiredTrue\">{{ 'errors.required' | translate }}</div>\r\n\t\t<div *ngIf=\"controlRef.errors.min\">{{ 'errors.min' | translate : { value: control.min } }}</div>\r\n\t\t<div *ngIf=\"controlRef.errors.max\">{{ 'errors.max' | translate : { value: control.max } }}</div>\r\n\t\t<div *ngIf=\"controlRef.errors.email\">{{ 'errors.email' | translate }}</div>\r\n\t\t<div *ngIf=\"controlRef.errors.minLength\">{{ 'errors.minLength' | translate : { value: control.minLength } }}</div>\r\n\t\t<div *ngIf=\"controlRef.errors.maxLength\">{{ 'errors.maxLength' | translate : { value: control.maxLength } }}</div>\r\n\t\t<!-- <div *ngIf=\"controlRef.errors.pattern\">{{ 'errors.pattern' | translate }}</div> -->\r\n\t\t<div *ngIf=\"controlRef.errors.match\">{{ 'errors.match' | translate }}</div>\r\n\t</div>\r\n</div>\r\n"}]}],"members":{"control":[{"__symbolic":"property","decorators":[{"__symbolic":"call","expression":{"__symbolic":"reference","module":"@angular/core","name":"Input","line":14,"character":2}}]}],"form":[{"__symbolic":"property","decorators":[{"__symbolic":"call","expression":{"__symbolic":"reference","module":"@angular/core","name":"Input","line":15,"character":2}}]}],"__ctor__":[{"__symbolic":"constructor","parameters":[{"__symbolic":"reference","module":"@angular/core","name":"Renderer2","line":24,"character":20}]}],"getFormattedValue":[{"__symbolic":"method"}],"onInput":[{"__symbolic":"method"}],"onFocus":[{"__symbolic":"method"}],"onBlur":[{"__symbolic":"method"}],"formatValue":[{"__symbolic":"method"}],"parseValue":[{"__symbolic":"method"}],"writeValue":[{"__symbolic":"method"}],"registerOnChange":[{"__symbolic":"method"}],"registerOnTouched":[{"__symbolic":"method"}],"setDisabledState":[{"__symbolic":"method"}]}},"ControlService":{"__symbolic":"class","decorators":[{"__symbolic":"call","expression":{"__symbolic":"reference","module":"@angular/core","name":"Injectable","line":5,"character":1},"arguments":[{"providedIn":"root"}]}],"members":{"getValidators":[{"__symbolic":"method"}],"toFormGroup":[{"__symbolic":"method"}]},"statics":{"ngInjectableDef":{}}},"ExistsValidator":{"__symbolic":"class","decorators":[{"__symbolic":"call","expression":{"__symbolic":"reference","module":"@angular/core","name":"Directive","line":7,"character":1},"arguments":[{"selector":"[exists][formControlName],[exists][formControl],[exists][ngModel]","providers":[{"provide":{"__symbolic":"reference","module":"@angular/forms","name":"NG_ASYNC_VALIDATORS","line":10,"character":13},"useExisting":{"__symbolic":"reference","name":"ExistsValidator"},"multi":true}]}]}],"members":{"exists":[{"__symbolic":"property","decorators":[{"__symbolic":"call","expression":{"__symbolic":"reference","module":"@angular/core","name":"Input","line":34,"character":2}}]}],"exists$":[{"__symbolic":"method"}],"validate":[{"__symbolic":"method"}]}},"FormService":{"__symbolic":"class","decorators":[{"__symbolic":"call","expression":{"__symbolic":"reference","module":"@angular/core","name":"Injectable","line":13,"character":1},"arguments":[{"providedIn":"root"}]}],"members":{"__ctor__":[{"__symbolic":"constructor","parameters":[{"__symbolic":"reference","name":"ControlService"}]}],"getControlsFromOptions":[{"__symbolic":"method"}],"getGroupFromOptions":[{"__symbolic":"method"}],"getGroupFromControls":[{"__symbolic":"method"}]},"statics":{"ngInjectableDef":{}}},"MatchValidator":{"__symbolic":"class","decorators":[{"__symbolic":"call","expression":{"__symbolic":"reference","module":"@angular/core","name":"Directive","line":3,"character":1},"arguments":[{"selector":"[match][formControlName],[match][formControl],[match][ngModel]","providers":[{"provide":{"__symbolic":"reference","module":"@angular/forms","name":"NG_VALIDATORS","line":6,"character":13},"useExisting":{"__symbolic":"reference","name":"MatchValidator"},"multi":true}]}]}],"members":{"__ctor__":[{"__symbolic":"constructor","parameterDecorators":[[{"__symbolic":"call","expression":{"__symbolic":"reference","module":"@angular/core","name":"Attribute","line":12,"character":3},"arguments":["match"]}],[{"__symbolic":"call","expression":{"__symbolic":"reference","module":"@angular/core","name":"Attribute","line":13,"character":3},"arguments":["reverse"]}]],"parameters":[{"__symbolic":"reference","name":"string"},{"__symbolic":"reference","name":"string"}]}],"validate":[{"__symbolic":"method"}]}},"UppercaseDirective":{"__symbolic":"class","decorators":[{"__symbolic":"call","expression":{"__symbolic":"reference","module":"@angular/core","name":"Directive","line":2,"character":1},"arguments":[{"selector":"[ngModel][uppercase]"}]}],"members":{"ngModelChange":[{"__symbolic":"property","decorators":[{"__symbolic":"call","expression":{"__symbolic":"reference","module":"@angular/core","name":"Output","line":6,"character":2}}]}],"onInputChange":[{"__symbolic":"method","decorators":[{"__symbolic":"call","expression":{"__symbolic":"reference","module":"@angular/core","name":"HostListener","line":9,"character":2},"arguments":["input",["$event"]]}]}]}},"HighlightPipe":{"__symbolic":"class","decorators":[{"__symbolic":"call","expression":{"__symbolic":"reference","module":"@angular/core","name":"Pipe","line":2,"character":1},"arguments":[{"name":"highlight"}]},{"__symbolic":"call","expression":{"__symbolic":"reference","module":"@angular/core","name":"Injectable","line":7,"character":1},"arguments":[{"providedIn":"root"}]}],"members":{"transform":[{"__symbolic":"method"}],"escapeRegexChars":[{"__symbolic":"method"}],"safeToString":[{"__symbolic":"method"}],"encodeHTML":[{"__symbolic":"method"}]},"statics":{"ngInjectableDef":{}}},"HttpResponseInterceptor":{"__symbolic":"class","decorators":[{"__symbolic":"call","expression":{"__symbolic":"reference","module":"@angular/core","name":"Injectable","line":10,"character":1},"arguments":[{"providedIn":"root"}]}],"members":{"__ctor__":[{"__symbolic":"constructor","parameters":[{"__symbolic":"reference","module":"@angular/core","name":"Injector","line":40,"character":20},{"__symbolic":"reference","name":"HttpStatusCodeService"}]}],"intercept":[{"__symbolic":"method"}]},"statics":{"ngInjectableDef":{}}},"HttpStatusCodeService":{"__symbolic":"class","decorators":[{"__symbolic":"call","expression":{"__symbolic":"reference","module":"@angular/core","name":"Injectable","line":2,"character":1}}],"members":{"__ctor__":[{"__symbolic":"constructor"}],"setStatusCode":[{"__symbolic":"method"}],"getStatusCode":[{"__symbolic":"method"}],"getRedirectUrl":[{"__symbolic":"method"}]}},"JsonFormatterComponent":{"__symbolic":"class","decorators":[{"__symbolic":"call","expression":{"__symbolic":"reference","module":"@angular/core","name":"Component","line":5,"character":1},"arguments":[{"selector":"json-formatter","template":"<div #jsonFormatter></div>","encapsulation":{"__symbolic":"select","expression":{"__symbolic":"reference","module":"@angular/core","name":"ViewEncapsulation","line":9,"character":16},"member":"Emulated"},"styles":[""]}]}],"members":{"input":[{"__symbolic":"property","decorators":[{"__symbolic":"call","expression":{"__symbolic":"reference","module":"@angular/core","name":"ViewChild","line":12,"character":2},"arguments":["jsonFormatter"]}]}],"json":[{"__symbolic":"property","decorators":[{"__symbolic":"call","expression":{"__symbolic":"reference","module":"@angular/core","name":"Input","line":14,"character":2}}]}],"__ctor__":[{"__symbolic":"constructor","parameterDecorators":[[{"__symbolic":"call","expression":{"__symbolic":"reference","module":"@angular/core","name":"Inject","line":19,"character":3},"arguments":[{"__symbolic":"reference","module":"@angular/core","name":"PLATFORM_ID","line":19,"character":10}]}]],"parameters":[{"__symbolic":"reference","name":"string"}]}],"ngOnChanges":[{"__symbolic":"method"}]}},"Label":{"__symbolic":"class","members":{}},"LabelAsyncPipe":{"__symbolic":"class","decorators":[{"__symbolic":"call","expression":{"__symbolic":"reference","module":"@angular/core","name":"Pipe","line":5,"character":1},"arguments":[{"name":"labelAsync","pure":false}]},{"__symbolic":"call","expression":{"__symbolic":"reference","module":"@angular/core","name":"Injectable","line":10,"character":1},"arguments":[{"providedIn":"root"}]}],"members":{"__ctor__":[{"__symbolic":"constructor","parameters":[{"__symbolic":"reference","module":"@angular/core","name":"ChangeDetectorRef","line":18,"character":26},{"__symbolic":"reference","name":"LabelService"}]}],"transform":[{"__symbolic":"method"}],"ngOnDestroy":[{"__symbolic":"method"}]},"statics":{"ngInjectableDef":{}}},"LabelDirective":{"__symbolic":"class","extends":{"__symbolic":"reference","name":"DisposableComponent"},"decorators":[{"__symbolic":"call","expression":{"__symbolic":"reference","module":"@angular/core","name":"Directive","line":6,"character":1},"arguments":[{"selector":"[label]"}]}],"members":{"label":[{"__symbolic":"property","decorators":[{"__symbolic":"call","expression":{"__symbolic":"reference","module":"@angular/core","name":"Input","line":19,"character":2}}]}],"labelParams":[{"__symbolic":"property","decorators":[{"__symbolic":"call","expression":{"__symbolic":"reference","module":"@angular/core","name":"Input","line":20,"character":2}}]}],"__ctor__":[{"__symbolic":"constructor","parameters":[{"__symbolic":"reference","module":"@angular/core","name":"ElementRef","line":23,"character":19},{"__symbolic":"reference","name":"LabelService"}]}],"ngOnInit":[{"__symbolic":"method"}]}},"LabelPipe":{"__symbolic":"class","decorators":[{"__symbolic":"call","expression":{"__symbolic":"reference","module":"@angular/core","name":"Pipe","line":4,"character":1},"arguments":[{"name":"label","pure":false}]},{"__symbolic":"call","expression":{"__symbolic":"reference","module":"@angular/core","name":"Injectable","line":9,"character":1},"arguments":[{"providedIn":"root"}]}],"members":{"__ctor__":[{"__symbolic":"constructor","parameters":[{"__symbolic":"reference","module":"@angular/core","name":"ChangeDetectorRef","line":15,"character":15},{"__symbolic":"reference","name":"LabelService"}]}],"transform":[{"__symbolic":"method"}]},"statics":{"ngInjectableDef":{}}},"LabelService":{"__symbolic":"class","arity":1,"extends":{"__symbolic":"reference","name":"ɵa"},"decorators":[{"__symbolic":"call","expression":{"__symbolic":"reference","module":"@angular/core","name":"Injectable","line":12,"character":1},"arguments":[{"providedIn":"root"}]}],"members":{"__ctor__":[{"__symbolic":"constructor","parameters":[{"__symbolic":"reference","module":"@angular/core","name":"Injector","line":49,"character":22}]}],"getTranslation":[{"__symbolic":"method"}],"getLabel":[{"__symbolic":"method"}],"parseLabel":[{"__symbolic":"method"}],"missingLabel":[{"__symbolic":"method"}],"parseParams":[{"__symbolic":"method"}],"getKey":[{"__symbolic":"method"}],"register":[{"__symbolic":"method"}],"collect":[{"__symbolic":"method"}],"collectKeys":[{"__symbolic":"method"}]},"statics":{"ngInjectableDef":{}}},"Logger":{"__symbolic":"class","decorators":[{"__symbolic":"call","expression":{"__symbolic":"reference","module":"@angular/core","name":"Injectable","line":8,"character":1},"arguments":[{"providedIn":"root"}]}],"members":{"__ctor__":[{"__symbolic":"constructor","parameters":[{"__symbolic":"reference","name":"CoreService"}]}],"request":[{"__symbolic":"method"}],"log":[{"__symbolic":"method"}],"warn":[{"__symbolic":"method"}],"error":[{"__symbolic":"method"}],"http":[{"__symbolic":"method"}],"clear":[{"__symbolic":"method"}]},"statics":{"ngInjectableDef":{}}},"LoggerComponent":{"__symbolic":"class","decorators":[{"__symbolic":"call","expression":{"__symbolic":"reference","module":"@angular/core","name":"Component","line":3,"character":1},"arguments":[{"selector":"core-logger","encapsulation":{"__symbolic":"select","expression":{"__symbolic":"reference","module":"@angular/core","name":"ViewEncapsulation","line":7,"character":16},"member":"Emulated"},"template":"<div class=\"error-http\" *ngIf=\"logger.httpError\">\n\t<span>error</span>&nbsp;\n\t<span class=\"status\">{{logger.httpError.status}}</span>&nbsp;\n\t<span class=\"url\">{{logger.httpError.url}}</span>&nbsp;\n\t<span class=\"message\">{{logger.httpError.body?.error}}</span>\n</div>\n<!--\n<div *ngIf=\"logger.logs.length\">\n\t<ul class=\"list-group \">\n\t\t<li class=\"list-group-item\">\n\t\t\t<button type=\"button\" class=\"btn btn-outline-primary btn-sm float-right\" (click)=\"logger.clear()\" title=\"Clear Logs\">{{ 'app.clear' | translate }}</button>\n\t\t</li>\n\t\t<li class=\"list-group-item\" *ngFor='let log of logger.logs'>\n\t\t\t<span>{{log}}</span>\n\t\t</li>\n\t</ul>\n\t<br>\n</div>\n-->\n","styles":[".error-http{padding:15px;max-width:1140px;margin:0 auto 10px;background:#faebd7;font-size:13px;font-family:monospace;color:#d2691e}"]}]}],"members":{"__ctor__":[{"__symbolic":"constructor","parameters":[{"__symbolic":"reference","name":"Logger"}]}],"ngOnInit":[{"__symbolic":"method"}]}},"Document":{"__symbolic":"class","members":{}},"DocumentIndex":{"__symbolic":"class","members":{}},"DocumentService":{"__symbolic":"class","arity":1,"extends":{"__symbolic":"reference","name":"EntityService"},"decorators":[{"__symbolic":"call","expression":{"__symbolic":"reference","module":"@angular/core","name":"Injectable","line":6,"character":1},"arguments":[{"providedIn":"root"}]}],"members":{"getDetailBySlug":[{"__symbolic":"method"}]},"statics":{"ngInjectableDef":{}}},"Entity":{"__symbolic":"class","members":{}},"EntityService":{"__symbolic":"class","arity":1,"extends":{"__symbolic":"reference","name":"IdentityService"},"decorators":[{"__symbolic":"call","expression":{"__symbolic":"reference","module":"@angular/core","name":"Injectable","line":5,"character":1},"arguments":[{"providedIn":"root"}]}],"members":{"getDetailByName":[{"__symbolic":"method"}]},"statics":{"ngInjectableDef":{}}},"EventDispatcherService":{"__symbolic":"class","decorators":[{"__symbolic":"call","expression":{"__symbolic":"reference","module":"@angular/core","name":"Injectable","line":9,"character":1},"arguments":[{"providedIn":"root"}]}],"members":{"__ctor__":[{"__symbolic":"constructor"}],"emit":[{"__symbolic":"method"}],"observe":[{"__symbolic":"method"}]},"statics":{"ngInjectableDef":{}}},"Feature":{"__symbolic":"class","members":{}},"Identity":{"__symbolic":"class","members":{}},"IdentityService":{"__symbolic":"class","arity":1,"extends":{"__symbolic":"reference","name":"ɵa"},"decorators":[{"__symbolic":"call","expression":{"__symbolic":"reference","module":"@angular/core","name":"Injectable","line":6,"character":1},"arguments":[{"providedIn":"root"}]}],"members":{"__ctor__":[{"__symbolic":"constructor","parameters":[{"__symbolic":"reference","module":"@angular/core","name":"Injector","line":12,"character":22}]}],"getList":[{"__symbolic":"method"}],"getDetailByIdNo404":[{"__symbolic":"method"}],"getDetailById":[{"__symbolic":"method"}],"add":[{"__symbolic":"method"}],"update":[{"__symbolic":"method"}]},"statics":{"ngInjectableDef":{}}},"Image":{"__symbolic":"class","members":{}},"ImageType":{"Default":1,"Gallery":2,"Share":3},"MenuItem":{"__symbolic":"class","members":{"__ctor__":[{"__symbolic":"constructor","parameters":[{"__symbolic":"reference","name":"any"}]}]}},"MenuService":{"__symbolic":"class","extends":{"__symbolic":"reference","name":"EntityService"},"decorators":[{"__symbolic":"call","expression":{"__symbolic":"reference","module":"@angular/core","name":"Injectable","line":4,"character":1},"arguments":[{"providedIn":"root"}]}],"members":{"__ctor__":[{"__symbolic":"constructor","parameters":[{"__symbolic":"reference","module":"@angular/core","name":"Injector","line":14,"character":22}]}]},"statics":{"ngInjectableDef":{}}},"Taxonomy":{"__symbolic":"class","members":{}},"OnceService":{"__symbolic":"class","decorators":[{"__symbolic":"call","expression":{"__symbolic":"reference","module":"@angular/core","name":"Injectable","line":7,"character":1},"arguments":[{"providedIn":"root"}]}],"members":{"__ctor__":[{"__symbolic":"constructor","parameterDecorators":[[{"__symbolic":"call","expression":{"__symbolic":"reference","module":"@angular/core","name":"Inject","line":16,"character":3},"arguments":[{"__symbolic":"reference","module":"@angular/core","name":"PLATFORM_ID","line":16,"character":10}]}],null],"parameters":[{"__symbolic":"reference","name":"string"},{"__symbolic":"reference","module":"@angular/core","name":"NgZone","line":17,"character":16}]}],"script":[{"__symbolic":"method"}]},"statics":{"ngInjectableDef":{}}},"AssetPipe":{"__symbolic":"class","decorators":[{"__symbolic":"call","expression":{"__symbolic":"reference","module":"@angular/core","name":"Pipe","line":4,"character":1},"arguments":[{"name":"asset"}]},{"__symbolic":"call","expression":{"__symbolic":"reference","module":"@angular/core","name":"Injectable","line":9,"character":1},"arguments":[{"providedIn":"root"}]}],"members":{"__ctor__":[{"__symbolic":"constructor","parameters":[{"__symbolic":"reference","name":"CoreService"},{"__symbolic":"reference","name":"SegmentPipe"}]}],"transform":[{"__symbolic":"method"}]},"statics":{"ngInjectableDef":{}}},"CustomAsyncPipe":{"__symbolic":"class","decorators":[{"__symbolic":"call","expression":{"__symbolic":"reference","module":"@angular/core","name":"Pipe","line":3,"character":1},"arguments":[{"name":"customAsync","pure":false}]}],"members":{"__ctor__":[{"__symbolic":"constructor","parameters":[{"__symbolic":"reference","module":"@angular/core","name":"ChangeDetectorRef","line":15,"character":26}]}],"transform":[{"__symbolic":"method"}],"observableToValue":[{"__symbolic":"method"}],"dispose":[{"__symbolic":"method"}],"ngOnDestroy":[{"__symbolic":"method"}],"_observableToValue":[{"__symbolic":"method"}]}},"ImageUrlPipe":{"__symbolic":"class","decorators":[{"__symbolic":"call","expression":{"__symbolic":"reference","module":"@angular/core","name":"Pipe","line":3,"character":1},"arguments":[{"name":"imageUrl"}]},{"__symbolic":"call","expression":{"__symbolic":"reference","module":"@angular/core","name":"Injectable","line":8,"character":1},"arguments":[{"providedIn":"root"}]}],"members":{"transform":[{"__symbolic":"method"}]},"statics":{"ngInjectableDef":{}}},"ImagePipe":{"__symbolic":"class","decorators":[{"__symbolic":"call","expression":{"__symbolic":"reference","module":"@angular/core","name":"Pipe","line":3,"character":1},"arguments":[{"name":"image"}]},{"__symbolic":"call","expression":{"__symbolic":"reference","module":"@angular/core","name":"Injectable","line":8,"character":1},"arguments":[{"providedIn":"root"}]}],"members":{"transform":[{"__symbolic":"method"}]},"statics":{"ngInjectableDef":{}}},"PublicPipe":{"__symbolic":"class","decorators":[{"__symbolic":"call","expression":{"__symbolic":"reference","module":"@angular/core","name":"Pipe","line":4,"character":1},"arguments":[{"name":"public"}]},{"__symbolic":"call","expression":{"__symbolic":"reference","module":"@angular/core","name":"Injectable","line":9,"character":1},"arguments":[{"providedIn":"root"}]}],"members":{"__ctor__":[{"__symbolic":"constructor","parameters":[{"__symbolic":"reference","name":"CoreService"},{"__symbolic":"reference","name":"SegmentPipe"}]}],"transform":[{"__symbolic":"method"}]},"statics":{"ngInjectableDef":{}}},"SegmentPipe":{"__symbolic":"class","decorators":[{"__symbolic":"call","expression":{"__symbolic":"reference","module":"@angular/core","name":"Pipe","line":4,"character":1},"arguments":[{"name":"segment"}]},{"__symbolic":"call","expression":{"__symbolic":"reference","module":"@angular/core","name":"Injectable","line":8,"character":1},"arguments":[{"providedIn":"root"}]}],"members":{"__ctor__":[{"__symbolic":"constructor","parameters":[{"__symbolic":"reference","module":"@angular/common","name":"Location","line":14,"character":20}]}],"transform":[{"__symbolic":"method"}]},"statics":{"ngInjectableDef":{}}},"RoutePipe":{"__symbolic":"class","decorators":[{"__symbolic":"call","expression":{"__symbolic":"reference","module":"@angular/core","name":"Pipe","line":3,"character":1},"arguments":[{"name":"route","pure":false}]},{"__symbolic":"call","expression":{"__symbolic":"reference","module":"@angular/core","name":"Injectable","line":8,"character":1},"arguments":[{"providedIn":"root"}]}],"members":{"__ctor__":[{"__symbolic":"constructor","parameters":[{"__symbolic":"reference","name":"RouteService"}]}],"transform":[{"__symbolic":"method"}]},"statics":{"ngInjectableDef":{}}},"RouteService":{"__symbolic":"class","decorators":[{"__symbolic":"call","expression":{"__symbolic":"reference","module":"@angular/core","name":"Injectable","line":15,"character":1},"arguments":[{"providedIn":"root"}]}],"members":{"__ctor__":[{"__symbolic":"constructor","parameterDecorators":[[{"__symbolic":"call","expression":{"__symbolic":"reference","module":"@angular/core","name":"Inject","line":34,"character":3},"arguments":[{"__symbolic":"reference","module":"@angular/core","name":"PLATFORM_ID","line":34,"character":10}]}],null,null,null,null,null,null,null],"parameters":[{"__symbolic":"reference","name":"string"},{"__symbolic":"reference","name":"CoreService"},{"__symbolic":"reference","module":"@angular/core","name":"Injector","line":36,"character":20},{"__symbolic":"reference","name":"ɵb"},{"__symbolic":"reference","module":"@angular/common","name":"Location","line":38,"character":20},{"__symbolic":"reference","module":"@angular/router","name":"ActivatedRoute","line":39,"character":17},{"__symbolic":"reference","module":"@angular/router","name":"Router","line":40,"character":18},{"__symbolic":"reference","name":"SegmentPipe"}]}],"getPageParams":[{"__symbolic":"method"}],"parseParams":[{"__symbolic":"method"}],"serializeParams":[{"__symbolic":"method"}],"parse":[{"__symbolic":"method"}],"serialize":[{"__symbolic":"method"}],"getId":[{"__symbolic":"method"}],"getSlug":[{"__symbolic":"method"}],"toRoute":[{"__symbolic":"method"}],"toSlug":[{"__symbolic":"method"}],"toParams":[{"__symbolic":"method"}],"toData":[{"__symbolic":"method"}],"setLanguage":[{"__symbolic":"method"}],"setLanguages":[{"__symbolic":"method"}],"subscribeToRouter":[{"__symbolic":"method"}],"detectLanguage":[{"__symbolic":"method"}],"getTime":[{"__symbolic":"method"}],"start":[{"__symbolic":"method"}],"end":[{"__symbolic":"method"}]},"statics":{"startTime":{"__symbolic":"error","message":"Variable not initialized","line":20,"character":8},"endTime":{"__symbolic":"error","message":"Variable not initialized","line":21,"character":8},"ngInjectableDef":{}}},"SlugAsyncPipe":{"__symbolic":"class","decorators":[{"__symbolic":"call","expression":{"__symbolic":"reference","module":"@angular/core","name":"Pipe","line":5,"character":1},"arguments":[{"name":"slugAsync","pure":false}]},{"__symbolic":"call","expression":{"__symbolic":"reference","module":"@angular/core","name":"Injectable","line":10,"character":1},"arguments":[{"providedIn":"root"}]}],"members":{"__ctor__":[{"__symbolic":"constructor","parameters":[{"__symbolic":"reference","module":"@angular/core","name":"ChangeDetectorRef","line":18,"character":26},{"__symbolic":"reference","name":"SlugService"},{"__symbolic":"reference","name":"RoutePipe"}]}],"transform":[{"__symbolic":"method"}],"ngOnDestroy":[{"__symbolic":"method"}]},"statics":{"ngInjectableDef":{}}},"SlugPipe":{"__symbolic":"class","decorators":[{"__symbolic":"call","expression":{"__symbolic":"reference","module":"@angular/core","name":"Pipe","line":4,"character":1},"arguments":[{"name":"slug","pure":false}]},{"__symbolic":"call","expression":{"__symbolic":"reference","module":"@angular/core","name":"Injectable","line":9,"character":1},"arguments":[{"providedIn":"root"}]}],"members":{"__ctor__":[{"__symbolic":"constructor","parameters":[{"__symbolic":"reference","name":"SlugService"}]}],"transform":[{"__symbolic":"method"}]},"statics":{"ngInjectableDef":{}}},"SlugService":{"__symbolic":"class","extends":{"__symbolic":"reference","name":"EntityService"},"decorators":[{"__symbolic":"call","expression":{"__symbolic":"reference","module":"@angular/core","name":"Injectable","line":6,"character":1},"arguments":[{"providedIn":"root"}]}],"members":{"getKey":[{"__symbolic":"method"}],"register":[{"__symbolic":"method"}],"collect":[{"__symbolic":"method"}],"getSlugs":[{"__symbolic":"method"}],"collectKeys":[{"__symbolic":"method"}]},"statics":{"ngInjectableDef":{}}},"CookieStorageService":{"__symbolic":"class","decorators":[{"__symbolic":"call","expression":{"__symbolic":"reference","module":"@angular/core","name":"Injectable","line":31,"character":1},"arguments":[{"providedIn":"root"}]}],"members":{"__ctor__":[{"__symbolic":"constructor","parameterDecorators":[[{"__symbolic":"call","expression":{"__symbolic":"reference","module":"@angular/core","name":"Inject","line":37,"character":3},"arguments":[{"__symbolic":"reference","module":"@angular/core","name":"PLATFORM_ID","line":37,"character":10}]}],null],"parameters":[{"__symbolic":"reference","name":"string"},{"__symbolic":"reference","name":"StorageService"}]}],"tryGet":[{"__symbolic":"method"}],"delete":[{"__symbolic":"method"}],"exist":[{"__symbolic":"method"}],"get":[{"__symbolic":"method"}],"set":[{"__symbolic":"method"}],"on":[{"__symbolic":"method"}],"setter":[{"__symbolic":"method"}],"isSupported":[{"__symbolic":"method"}]},"statics":{"ngInjectableDef":{}}},"LocalStorageService":{"__symbolic":"class","decorators":[{"__symbolic":"call","expression":{"__symbolic":"reference","module":"@angular/core","name":"Injectable","line":253,"character":1},"arguments":[{"providedIn":"root"}]}],"members":{"__ctor__":[{"__symbolic":"constructor","parameterDecorators":[[{"__symbolic":"call","expression":{"__symbolic":"reference","module":"@angular/core","name":"Inject","line":259,"character":3},"arguments":[{"__symbolic":"reference","module":"@angular/core","name":"PLATFORM_ID","line":259,"character":10}]}],null],"parameters":[{"__symbolic":"reference","name":"string"},{"__symbolic":"reference","name":"CookieStorageService"}]}],"tryGet":[{"__symbolic":"method"}],"delete":[{"__symbolic":"method"}],"exist":[{"__symbolic":"method"}],"get":[{"__symbolic":"method"}],"on":[{"__symbolic":"method"}],"set":[{"__symbolic":"method"}],"isSupported":[{"__symbolic":"method"}]},"statics":{"ngInjectableDef":{}}},"SessionStorageService":{"__symbolic":"class","decorators":[{"__symbolic":"call","expression":{"__symbolic":"reference","module":"@angular/core","name":"Injectable","line":142,"character":1},"arguments":[{"providedIn":"root"}]}],"members":{"__ctor__":[{"__symbolic":"constructor","parameterDecorators":[[{"__symbolic":"call","expression":{"__symbolic":"reference","module":"@angular/core","name":"Inject","line":148,"character":3},"arguments":[{"__symbolic":"reference","module":"@angular/core","name":"PLATFORM_ID","line":148,"character":10}]}],null],"parameters":[{"__symbolic":"reference","name":"string"},{"__symbolic":"reference","name":"CookieStorageService"}]}],"tryGet":[{"__symbolic":"method"}],"delete":[{"__symbolic":"method"}],"exist":[{"__symbolic":"method"}],"get":[{"__symbolic":"method"}],"on":[{"__symbolic":"method"}],"set":[{"__symbolic":"method"}],"isSupported":[{"__symbolic":"method"}]},"statics":{"ngInjectableDef":{}}},"StorageService":{"__symbolic":"class","decorators":[{"__symbolic":"call","expression":{"__symbolic":"reference","module":"@angular/core","name":"Injectable","line":16,"character":1},"arguments":[{"providedIn":"root"}]}],"members":{"delete":[{"__symbolic":"method"}],"exist":[{"__symbolic":"method"}],"get":[{"__symbolic":"method"}],"set":[{"__symbolic":"method"}],"on":[{"__symbolic":"method"}],"tryGet":[{"__symbolic":"method"}]},"statics":{"ngInjectableDef":{}}},"TranslatePipe":{"__symbolic":"class","decorators":[{"__symbolic":"call","expression":{"__symbolic":"reference","module":"@angular/core","name":"Pipe","line":3,"character":1},"arguments":[{"name":"translate","pure":false}]},{"__symbolic":"call","expression":{"__symbolic":"reference","module":"@angular/core","name":"Injectable","line":8,"character":1},"arguments":[{"providedIn":"root"}]}],"members":{"__ctor__":[{"__symbolic":"constructor","parameters":[{"__symbolic":"reference","module":"@angular/core","name":"ChangeDetectorRef","line":14,"character":15},{"__symbolic":"reference","name":"ɵb"}]}],"transform":[{"__symbolic":"method"}]},"statics":{"ngInjectableDef":{}}},"SafeStylePipe":{"__symbolic":"class","decorators":[{"__symbolic":"call","expression":{"__symbolic":"reference","module":"@angular/core","name":"Pipe","line":3,"character":1},"arguments":[{"name":"safeStyle"}]},{"__symbolic":"call","expression":{"__symbolic":"reference","module":"@angular/core","name":"Injectable","line":7,"character":1},"arguments":[{"providedIn":"root"}]}],"members":{"__ctor__":[{"__symbolic":"constructor","parameters":[{"__symbolic":"reference","module":"@angular/platform-browser","name":"DomSanitizer","line":13,"character":21}]}],"transform":[{"__symbolic":"method"}]},"statics":{"ngInjectableDef":{}}},"SafeUrlPipe":{"__symbolic":"class","decorators":[{"__symbolic":"call","expression":{"__symbolic":"reference","module":"@angular/core","name":"Pipe","line":3,"character":1},"arguments":[{"name":"safeUrl"}]},{"__symbolic":"call","expression":{"__symbolic":"reference","module":"@angular/core","name":"Injectable","line":7,"character":1},"arguments":[{"providedIn":"root"}]}],"members":{"__ctor__":[{"__symbolic":"constructor","parameters":[{"__symbolic":"reference","module":"@angular/platform-browser","name":"DomSanitizer","line":13,"character":21}]}],"transform":[{"__symbolic":"method"}]},"statics":{"ngInjectableDef":{}}},"TrustPipe":{"__symbolic":"class","decorators":[{"__symbolic":"call","expression":{"__symbolic":"reference","module":"@angular/core","name":"Pipe","line":3,"character":1},"arguments":[{"name":"safeHtml"}]}],"members":{"__ctor__":[{"__symbolic":"constructor","parameters":[{"__symbolic":"reference","module":"@angular/platform-browser","name":"DomSanitizer","line":9,"character":21}]}],"transform":[{"__symbolic":"method"}]}},"ɵa":{"__symbolic":"class","arity":1,"decorators":[{"__symbolic":"call","expression":{"__symbolic":"reference","module":"@angular/core","name":"Injectable","line":22,"character":1},"arguments":[{"providedIn":"root"}]}],"members":{"__ctor__":[{"__symbolic":"constructor","parameters":[{"__symbolic":"reference","module":"@angular/core","name":"Injector","line":89,"character":22}]}],"getUrl":[{"__symbolic":"method"}],"get":[{"__symbolic":"method"}],"post":[{"__symbolic":"method"}],"put":[{"__symbolic":"method"}],"patch":[{"__symbolic":"method"}],"delete":[{"__symbolic":"method"}],"toCamelCase":[{"__symbolic":"method"}],"getStateKey":[{"__symbolic":"method"}],"stateGet":[{"__symbolic":"method"}],"statePost":[{"__symbolic":"method"}]},"statics":{"ngInjectableDef":{}}},"ɵb":{"__symbolic":"class","extends":{"__symbolic":"reference","name":"ɵa"},"decorators":[{"__symbolic":"call","expression":{"__symbolic":"reference","module":"@angular/core","name":"Injectable","line":9,"character":1},"arguments":[{"providedIn":"root"}]}],"members":{"__ctor__":[{"__symbolic":"constructor","parameters":[{"__symbolic":"reference","module":"@angular/core","name":"Injector","line":19,"character":22}]}],"use":[{"__symbolic":"method"}],"setDefaultLang":[{"__symbolic":"method"}],"addLangs":[{"__symbolic":"method"}],"getBrowserLang":[{"__symbolic":"method"}]},"statics":{"ngInjectableDef":{}}}},"origins":{"AuthService":"./lib/auth/auth.service","AuthStrategy":"./lib/auth/auth.service","CoreConfig":"./lib/config/core.config","CORE_CONFIG":"./lib/config/core.config","CoreService":"./lib/config/core.service","DefaultContentDirective":"./lib/content/default-content.directive","CoreModuleComponent":"./lib/core-module.component","CoreModule":"./lib/core.module","DisposableComponent":"./lib/disposable/disposable.component","ControlBase":"./lib/forms/controls/control-base","ControlBaseOptions":"./lib/forms/controls/control-base","ControlComponent":"./lib/forms/controls/control.component","ControlService":"./lib/forms/controls/control.service","ExistsValidator":"./lib/forms/exists.validator","FormService":"./lib/forms/form.service","MatchValidator":"./lib/forms/match.validator","UppercaseDirective":"./lib/forms/uppercase.directive","HighlightPipe":"./lib/highlight/highlight.pipe","HttpResponseInterceptor":"./lib/http/http-response.interceptor","HttpStatusCodeService":"./lib/http/http-status-code.service","JsonFormatterComponent":"./lib/json-formatter/json-formatter.component","Label":"./lib/labels/label","LabelAsyncPipe":"./lib/labels/label-async.pipe","LabelDirective":"./lib/labels/label.directive","LabelPipe":"./lib/labels/label.pipe","LabelService":"./lib/labels/label.service","Logger":"./lib/logger/logger","LoggerComponent":"./lib/logger/logger.component","Document":"./lib/models/document","DocumentIndex":"./lib/models/document","DocumentService":"./lib/models/document.service","Entity":"./lib/models/entity","EntityService":"./lib/models/entity.service","EventDispatcherService":"./lib/models/event-dispatcher.service","Feature":"./lib/models/feature","Identity":"./lib/models/identity","IdentityService":"./lib/models/identity.service","Image":"./lib/models/image","ImageType":"./lib/models/image","MenuItem":"./lib/models/menu-item","MenuService":"./lib/models/menu.service","Taxonomy":"./lib/models/taxonomy","OnceService":"./lib/once/once.service","AssetPipe":"./lib/pipes/asset.pipe","CustomAsyncPipe":"./lib/pipes/custom-async.pipe","ImageUrlPipe":"./lib/pipes/image-url.pipe","ImagePipe":"./lib/pipes/image.pipe","PublicPipe":"./lib/pipes/public.pipe","SegmentPipe":"./lib/pipes/segment.pipe","RoutePipe":"./lib/route/route.pipe","RouteService":"./lib/route/route.service","SlugAsyncPipe":"./lib/slug/slug-async.pipe","SlugPipe":"./lib/slug/slug.pipe","SlugService":"./lib/slug/slug.service","CookieStorageService":"./lib/storage/storage.service","LocalStorageService":"./lib/storage/storage.service","SessionStorageService":"./lib/storage/storage.service","StorageService":"./lib/storage/storage.service","TranslatePipe":"./lib/translate/translate.pipe","SafeStylePipe":"./lib/trust/safe-style.pipe","SafeUrlPipe":"./lib/trust/safe-url.pipe","TrustPipe":"./lib/trust/trust.pipe","ɵa":"./lib/api/api.service","ɵb":"./lib/translate/translate.service"},"importAs":"@designr/core"}